ess/__init__.py
ess/nexus.py
ess_nexus-0.6.dist-info/LICENSE
ess_nexus-0.6.dist-info/METADATA
ess_nexus-0.6.dist-info/WHEEL
ess_nexus-0.6.dist-info/top_level.txt
ess_nexus-0.6.dist-info/RECORD
