Metadata-Version: 2.1
Name: ess-nexus
Version: 0.6
Summary: Utility class for saving nexus files on ESS data format
Home-page: UNKNOWN
Author: Natalia Milas
Author-email: natalia.milas@ess.eu
License: MIT
Platform: UNKNOWN
Classifier: Programming Language :: Python :: 3
Classifier: License :: OSI Approved :: MIT License
Classifier: Operating System :: OS Independent
